pytest_docker_tools/__init__.py
pytest_docker_tools/builder.py
pytest_docker_tools/exceptions.py
pytest_docker_tools/plugin.py
pytest_docker_tools/templates.py
pytest_docker_tools/utils.py
pytest_docker_tools/contexts/scratch/Dockerfile
pytest_docker_tools/factories/__init__.py
pytest_docker_tools/factories/build.py
pytest_docker_tools/factories/container.py
pytest_docker_tools/factories/fetch.py
pytest_docker_tools/factories/image.py
pytest_docker_tools/factories/image_or_build.py
pytest_docker_tools/factories/network.py
pytest_docker_tools/factories/volume.py
pytest_docker_tools/wrappers/__init__.py
pytest_docker_tools/wrappers/container.py
pytest_docker_tools-3.1.9.dist-info/LICENSE
pytest_docker_tools-3.1.9.dist-info/METADATA
pytest_docker_tools-3.1.9.dist-info/WHEEL
pytest_docker_tools-3.1.9.dist-info/entry_points.txt
pytest_docker_tools-3.1.9.dist-info/top_level.txt
pytest_docker_tools-3.1.9.dist-info/RECORD
