Metadata-Version: 2.2
Name: pytest_docker_tools
Version: 3.1.9
Summary: Docker integration tests for pytest
Author-email: John Carr <john.carr@unrouted.co.uk>
License: Apache-2.0
Project-URL: homepage, https://github.com/Jc2k/pytest-docker-tools
Keywords: devops,docker,pytest
Platform: any
Classifier: License :: OSI Approved :: Apache Software License
Classifier: Topic :: Software Development :: Testing
Classifier: Intended Audience :: Developers
Classifier: Programming Language :: Python :: 3.9
Classifier: Programming Language :: Python :: 3.10
Classifier: Programming Language :: Python :: 3.11
Classifier: Programming Language :: Python :: 3.12
Classifier: Development Status :: 4 - Beta
Requires-Python: <4.0.0,>=3.9.0
License-File: LICENSE
Requires-Dist: pytest>=6.0.1
Requires-Dist: docker>=4.3.1
